LICENSE
MANIFEST.in
README.md
package.json
setup.py
dash_modalable/DashModalable.py
dash_modalable/__init__.py
dash_modalable/_imports_.py
dash_modalable/dash_modalable.min.js
dash_modalable/dash_modalable.min.js.map
dash_modalable/metadata.json
dash_modalable/package-info.json
dash_modalable.egg-info/PKG-INFO
dash_modalable.egg-info/SOURCES.txt
dash_modalable.egg-info/dependency_links.txt
dash_modalable.egg-info/top_level.txt
tests/test_usage.py