Metadata-Version: 2.1
Name: dash-modalable
Version: 0.0.5
Summary: Project Description
Author: mapix <mapix.me@gmail.com>
License: MIT
Classifier: Framework :: Dash
License-File: LICENSE
